main.py
core/__init__.py
core/data_handler.py
core/processing.py
seisplotpy-1.0.0.dist-info/licenses/LICENSE
ui/__init__.py
ui/dialogs.py
ui/header_tools.py
ui/horizon_manager.py
ui/seismic_view.py
seisplotpy-1.0.0.dist-info/METADATA
seisplotpy-1.0.0.dist-info/WHEEL
seisplotpy-1.0.0.dist-info/entry_points.txt
seisplotpy-1.0.0.dist-info/top_level.txt
seisplotpy-1.0.0.dist-info/RECORD
