Metadata-Version: 2.4
Name: SeisPlotPy
Version: 1.0.0
Summary: A high-performance 2D post-stack Interpretation & QC Workstation.
Home-page: https://github.com/arjun-vh/SeisPlotPy
Author: Arjun V H
Author-email: arjunvelliyidathu@gmail.com
Keywords: seismic,segy,geophysics,visualization
Classifier: Programming Language :: Python :: 3
Classifier: License :: OSI Approved :: GNU General Public License v2 (GPLv2)
Classifier: Operating System :: OS Independent
Classifier: Topic :: Scientific/Engineering
Classifier: Topic :: Scientific/Engineering :: Physics
Requires-Python: >=3.8
License-File: LICENSE
Requires-Dist: PyQt6>=6.4.0
Requires-Dist: pyqtgraph>=0.13.0
Requires-Dist: segyio>=1.9.0
Requires-Dist: numpy>=1.21.0
Requires-Dist: matplotlib>=3.5.0
Requires-Dist: pandas>=1.3.0
Requires-Dist: scipy>=1.10.0
Dynamic: author
Dynamic: author-email
Dynamic: classifier
Dynamic: description
Dynamic: description-content-type
Dynamic: home-page
Dynamic: keywords
Dynamic: license-file
Dynamic: requires-dist
Dynamic: requires-python
Dynamic: summary
